unzipping/__init__.py
unzipping-1.0.3.dist-info/WHEEL
unzipping-1.0.3.dist-info/METADATA
unzipping-1.0.3.dist-info/RECORD
