Metadata-Version: 2.3
Name: unzipping
Version: 1.0.3
Summary: The inverse of zip, including for empty iterables.
Keywords: empty,unzip,zip
Author: John Dawson
Author-email: John Dawson <john.a.dawson@proton.me>
License:                     GNU GENERAL PUBLIC LICENSE
Maintainer: John Dawson
Maintainer-email: John Dawson <john.a.dawson@proton.me>
Project-URL: Documentation, https://github.com/JohnADawson/unzipping/blob/master/src/unzipping/__init__.py
Project-URL: Homepage, https://github.com/JohnADawson/unzipping
